pyoptics
