Metadata-Version: 2.1
Name: pyoptics
Version: 0.0.5
Summary: Particle Beam Optics Tools
Home-page: https://github.com/rdemaria/pyoptics
Author: Riccardo De Maria
Author-email: riccardo.de.maria@cern.ch
Requires-Dist: numpy
Requires-Dist: matplotlib
Requires-Dist: cpymad
Requires-Dist: scipy
Requires-Dist: h5py
Requires-Dist: numba
Requires-Dist: pandas
Requires-Dist: xdeps
